x_clip/__init__.py
x_clip/distributed.py
x_clip/mlm.py
x_clip/tokenizer.py
x_clip/visual_ssl.py
x_clip/x_clip.py
x_clip/data/bpe_simple_vocab_16e6.txt
x_clip-0.14.4.dist-info/LICENSE
x_clip-0.14.4.dist-info/METADATA
x_clip-0.14.4.dist-info/WHEEL
x_clip-0.14.4.dist-info/top_level.txt
x_clip-0.14.4.dist-info/RECORD
