Metadata-Version: 2.1
Name: x-clip
Version: 0.14.4
Summary: X-CLIP
Home-page: https://github.com/lucidrains/x-clip
Author: Phil Wang
Author-email: lucidrains@gmail.com
License: MIT
Keywords: artificial intelligence,deep learning,contrastive learning,CLIP
Classifier: Development Status :: 4 - Beta
Classifier: Intended Audience :: Developers
Classifier: Topic :: Scientific/Engineering :: Artificial Intelligence
Classifier: License :: OSI Approved :: MIT License
Classifier: Programming Language :: Python :: 3.6
License-File: LICENSE
Requires-Dist: beartype
Requires-Dist: einops >=0.6
Requires-Dist: ftfy
Requires-Dist: regex
Requires-Dist: torch >=1.6
Requires-Dist: torchvision
